[
	{
		"address": "524-170 Egestas. St.",
		"region": "Ninh Bình",
		"postalZip": "4561",
		"country": "Philippines",
		"currency": "$9,291.13"
	},
	{
		"address": "407-1151 Nostra, Road",
		"region": "Podkarpackie",
		"postalZip": "343784",
		"country": "Italy",
		"currency": "$3,940.48"
	},
	{
		"address": "348-4417 Est Avenue",
		"region": "Alsace",
		"postalZip": "53-885",
		"country": "Chile",
		"currency": "$616.69"
	},
	{
		"address": "644-4589 Libero. Rd.",
		"region": "Valle del Cauca",
		"postalZip": "7980-2262",
		"country": "South Africa",
		"currency": "$6,253.39"
	},
	{
		"address": "P.O. Box 225, 1064 Sed St.",
		"region": "Irkutsk Oblast",
		"postalZip": "6520",
		"country": "Austria",
		"currency": "$3,020.85"
	},
	{
		"address": "7857 Magna Rd.",
		"region": "Victoria",
		"postalZip": "95-32",
		"country": "India",
		"currency": "$8,129.79"
	},
	{
		"address": "513-9795 Integer Rd.",
		"region": "Santa Catarina",
		"postalZip": "3626",
		"country": "Sweden",
		"currency": "$5,585.46"
	},
	{
		"address": "4001 Pede, Av.",
		"region": "Vorarlberg",
		"postalZip": "38437-78796",
		"country": "Nigeria",
		"currency": "$2,602.84"
	},
	{
		"address": "Ap #803-5020 Dolor Rd.",
		"region": "Sinaloa",
		"postalZip": "926677",
		"country": "France",
		"currency": "$819.48"
	},
	{
		"address": "952-6003 Lobortis Av.",
		"region": "North Island",
		"postalZip": "7278",
		"country": "Peru",
		"currency": "$3,054.58"
	},
	{
		"address": "Ap #609-5671 Penatibus Rd.",
		"region": "West Nusa Tenggara",
		"postalZip": "402218",
		"country": "Turkey",
		"currency": "$4,245.30"
	},
	{
		"address": "528-8253 Eget, Street",
		"region": "North Chungcheong",
		"postalZip": "347361",
		"country": "France",
		"currency": "$4,772.37"
	},
	{
		"address": "Ap #730-6633 Vel Avenue",
		"region": "East Region",
		"postalZip": "399033",
		"country": "Colombia",
		"currency": "$1,684.84"
	},
	{
		"address": "772-5635 Odio. Rd.",
		"region": "Dnipropetrovsk oblast",
		"postalZip": "51202",
		"country": "Germany",
		"currency": "$1,598.93"
	},
	{
		"address": "P.O. Box 386, 4413 Malesuada Avenue",
		"region": "Guanacaste",
		"postalZip": "4411",
		"country": "Colombia",
		"currency": "$7,441.19"
	},
	{
		"address": "Ap #617-3577 Nec Road",
		"region": "North Island",
		"postalZip": "96175-76607",
		"country": "Turkey",
		"currency": "$5,601.61"
	},
	{
		"address": "Ap #453-4587 Amet, St.",
		"region": "Abruzzo",
		"postalZip": "1371 PK",
		"country": "Australia",
		"currency": "$2,244.24"
	},
	{
		"address": "P.O. Box 559, 4798 Nisl. Avenue",
		"region": "Kocaeli",
		"postalZip": "35268",
		"country": "South Africa",
		"currency": "$6,090.10"
	},
	{
		"address": "372 Iaculis Rd.",
		"region": "Ogun",
		"postalZip": "888184",
		"country": "Brazil",
		"currency": "$7,061.04"
	},
	{
		"address": "Ap #153-2784 Donec Ave",
		"region": "West Sulawesi",
		"postalZip": "2659",
		"country": "Poland",
		"currency": "$3,511.13"
	},
	{
		"address": "P.O. Box 354, 1232 Tempus Road",
		"region": "Pomorskie",
		"postalZip": "237653",
		"country": "Poland",
		"currency": "$4,295.93"
	},
	{
		"address": "822-3292 Magna. Avenue",
		"region": "Lubuskie",
		"postalZip": "733272",
		"country": "Brazil",
		"currency": "$618.04"
	},
	{
		"address": "199-1281 Volutpat Rd.",
		"region": "Central Luzon",
		"postalZip": "3751-9323",
		"country": "Italy",
		"currency": "$1,127.74"
	},
	{
		"address": "Ap #351-2311 Fringilla Av.",
		"region": "Piemonte",
		"postalZip": "1745 OD",
		"country": "Turkey",
		"currency": "$4,815.29"
	},
	{
		"address": "Ap #916-2760 Ut Rd.",
		"region": "Midlothian",
		"postalZip": "7504",
		"country": "Poland",
		"currency": "$2,960.50"
	},
	{
		"address": "6825 Cubilia Rd.",
		"region": "Rivers",
		"postalZip": "A2E 8G8",
		"country": "United States",
		"currency": "$1,445.25"
	},
	{
		"address": "P.O. Box 992, 2138 Sed, St.",
		"region": "Namen",
		"postalZip": "10345",
		"country": "United States",
		"currency": "$5,894.89"
	},
	{
		"address": "7933 Fermentum Rd.",
		"region": "Limousin",
		"postalZip": "1282",
		"country": "Costa Rica",
		"currency": "$8,204.96"
	},
	{
		"address": "218-5604 Eu, Rd.",
		"region": "Kayseri",
		"postalZip": "50503",
		"country": "Nigeria",
		"currency": "$5,800.12"
	},
	{
		"address": "4944 Mauris Av.",
		"region": "Navarra",
		"postalZip": "46492",
		"country": "China",
		"currency": "$7,768.28"
	},
	{
		"address": "6263 Vel Avenue",
		"region": "Madrid",
		"postalZip": "2821 MN",
		"country": "South Africa",
		"currency": "$6,298.73"
	},
	{
		"address": "Ap #433-3174 Eu, Av.",
		"region": "Córdoba",
		"postalZip": "01875",
		"country": "India",
		"currency": "$1,344.71"
	},
	{
		"address": "630-4386 Pede. Road",
		"region": "North Kalimantan",
		"postalZip": "46988",
		"country": "China",
		"currency": "$5,312.73"
	},
	{
		"address": "Ap #437-4238 Nec, Av.",
		"region": "Mykolaiv oblast",
		"postalZip": "5842",
		"country": "Germany",
		"currency": "$2,068.59"
	},
	{
		"address": "Ap #464-4164 Vestibulum Av.",
		"region": "South Island",
		"postalZip": "12578",
		"country": "United Kingdom",
		"currency": "$716.22"
	},
	{
		"address": "P.O. Box 361, 1922 Sit Rd.",
		"region": "Campania",
		"postalZip": "64317",
		"country": "Australia",
		"currency": "$4,159.05"
	},
	{
		"address": "P.O. Box 288, 2344 Nonummy Rd.",
		"region": "Kujawsko-pomorskie",
		"postalZip": "269944",
		"country": "Pakistan",
		"currency": "$5,714.51"
	},
	{
		"address": "P.O. Box 390, 3762 Mi Avenue",
		"region": "Jigawa",
		"postalZip": "T4N 5P3",
		"country": "Peru",
		"currency": "$8,626.44"
	},
	{
		"address": "3695 Sed Road",
		"region": "Illes Balears",
		"postalZip": "11799",
		"country": "Indonesia",
		"currency": "$6,676.45"
	},
	{
		"address": "6678 Duis Rd.",
		"region": "Tabasco",
		"postalZip": "358575",
		"country": "China",
		"currency": "$6,013.34"
	},
	{
		"address": "223-8010 Dictum St.",
		"region": "North Island",
		"postalZip": "266488",
		"country": "India",
		"currency": "$8,371.14"
	},
	{
		"address": "3366 Nunc St.",
		"region": "Central Region",
		"postalZip": "885198",
		"country": "Nigeria",
		"currency": "$2,402.20"
	},
	{
		"address": "735-8351 Arcu. St.",
		"region": "Louisiana",
		"postalZip": "476742",
		"country": "Mexico",
		"currency": "$9,746.72"
	},
	{
		"address": "Ap #913-1910 Nunc Avenue",
		"region": "Oyo",
		"postalZip": "702657",
		"country": "Sweden",
		"currency": "$9,521.39"
	},
	{
		"address": "P.O. Box 776, 7622 Suspendisse Street",
		"region": "Basse-Normandie",
		"postalZip": "6688",
		"country": "Nigeria",
		"currency": "$675.76"
	},
	{
		"address": "Ap #779-3340 Fusce Road",
		"region": "Puntarenas",
		"postalZip": "84358-27625",
		"country": "Costa Rica",
		"currency": "$9,493.78"
	},
	{
		"address": "Ap #316-2026 Cursus. Road",
		"region": "Mexico City",
		"postalZip": "35850",
		"country": "Australia",
		"currency": "$3,104.19"
	},
	{
		"address": "P.O. Box 360, 8226 Mauris Avenue",
		"region": "Troms og Finnmark",
		"postalZip": "284232",
		"country": "Russian Federation",
		"currency": "$8,235.74"
	},
	{
		"address": "Ap #586-9993 Auctor Av.",
		"region": "KwaZulu-Natal",
		"postalZip": "551736",
		"country": "India",
		"currency": "$9,286.91"
	},
	{
		"address": "420-5667 Libero St.",
		"region": "Tyumen Oblast",
		"postalZip": "50213",
		"country": "Vietnam",
		"currency": "$7,737.05"
	},
	{
		"address": "108-4709 Iaculis, St.",
		"region": "Victoria",
		"postalZip": "37616",
		"country": "India",
		"currency": "$3,787.81"
	},
	{
		"address": "Ap #886-3566 Enim Street",
		"region": "Eastern Cape",
		"postalZip": "57-55",
		"country": "Singapore",
		"currency": "$6,430.66"
	},
	{
		"address": "P.O. Box 689, 9692 Ac, Rd.",
		"region": "Minas Gerais",
		"postalZip": "505513",
		"country": "Turkey",
		"currency": "$4,596.64"
	},
	{
		"address": "304-171 Ultrices Av.",
		"region": "Araucanía",
		"postalZip": "1223",
		"country": "India",
		"currency": "$1,613.55"
	},
	{
		"address": "119-2701 Consequat Avenue",
		"region": "Leinster",
		"postalZip": "8671",
		"country": "Ireland",
		"currency": "$2,154.59"
	},
	{
		"address": "297-7399 Donec Avenue",
		"region": "Connacht",
		"postalZip": "333546",
		"country": "Canada",
		"currency": "$601.29"
	},
	{
		"address": "114-7915 Semper. Street",
		"region": "Prince Edward Island",
		"postalZip": "314319",
		"country": "Indonesia",
		"currency": "$5,254.33"
	},
	{
		"address": "4977 Tincidunt, Road",
		"region": "Belgorod Oblast",
		"postalZip": "29283",
		"country": "Chile",
		"currency": "$922.77"
	},
	{
		"address": "Ap #110-5732 Scelerisque Road",
		"region": "KwaZulu-Natal",
		"postalZip": "3268",
		"country": "Canada",
		"currency": "$1,662.93"
	},
	{
		"address": "8297 Eget, Rd.",
		"region": "Khyber Pakhtoonkhwa",
		"postalZip": "473540",
		"country": "Canada",
		"currency": "$6,124.28"
	},
	{
		"address": "687-3662 Nullam Road",
		"region": "Kent",
		"postalZip": "9375",
		"country": "China",
		"currency": "$2,825.30"
	},
	{
		"address": "Ap #380-6828 Sed St.",
		"region": "Arica y Parinacota",
		"postalZip": "8310",
		"country": "India",
		"currency": "$7,121.02"
	},
	{
		"address": "333-4305 Dolor. Street",
		"region": "Sardegna",
		"postalZip": "R8L 9P1",
		"country": "Poland",
		"currency": "$2,838.97"
	},
	{
		"address": "Ap #816-2153 Nec, Av.",
		"region": "Stockholms län",
		"postalZip": "8650",
		"country": "Norway",
		"currency": "$9,226.53"
	},
	{
		"address": "261-8040 Ut, St.",
		"region": "East Region",
		"postalZip": "00471-55755",
		"country": "Sweden",
		"currency": "$1,695.64"
	},
	{
		"address": "574-6576 Vivamus St.",
		"region": "North Island",
		"postalZip": "43172",
		"country": "Australia",
		"currency": "$4,165.81"
	},
	{
		"address": "827-8450 Mus. Street",
		"region": "Munster",
		"postalZip": "1290",
		"country": "Austria",
		"currency": "$3,814.29"
	},
	{
		"address": "505-2360 Consectetuer Avenue",
		"region": "Rogaland",
		"postalZip": "77804",
		"country": "China",
		"currency": "$9,325.07"
	},
	{
		"address": "P.O. Box 508, 7239 Nonummy Rd.",
		"region": "Henegouwen",
		"postalZip": "387661",
		"country": "China",
		"currency": "$8,097.67"
	},
	{
		"address": "194-2854 Nec Road",
		"region": "Cordillera Administrative Region",
		"postalZip": "52460",
		"country": "Vietnam",
		"currency": "$6,353.74"
	},
	{
		"address": "P.O. Box 876, 6742 Porttitor Road",
		"region": "Free State",
		"postalZip": "33308-44445",
		"country": "Turkey",
		"currency": "$8,322.02"
	},
	{
		"address": "Ap #143-7688 Nam St.",
		"region": "Delta",
		"postalZip": "N81 7RD",
		"country": "Nigeria",
		"currency": "$2,430.62"
	},
	{
		"address": "Ap #255-3406 Tincidunt. Avenue",
		"region": "Queensland",
		"postalZip": "347733",
		"country": "Turkey",
		"currency": "$2,679.92"
	},
	{
		"address": "P.O. Box 668, 3194 Mattis St.",
		"region": "Nordrhein-Westphalen",
		"postalZip": "459181",
		"country": "Sweden",
		"currency": "$1,444.63"
	},
	{
		"address": "Ap #954-737 Sociis Avenue",
		"region": "La Libertad",
		"postalZip": "226442",
		"country": "Ukraine",
		"currency": "$5,146.72"
	},
	{
		"address": "373-2110 Velit. St.",
		"region": "Putumayo",
		"postalZip": "18543",
		"country": "Italy",
		"currency": "$2,796.51"
	},
	{
		"address": "8748 Sit St.",
		"region": "North Region",
		"postalZip": "75214",
		"country": "China",
		"currency": "$4,679.85"
	},
	{
		"address": "P.O. Box 678, 7357 Varius. St.",
		"region": "North Region",
		"postalZip": "L83 3MU",
		"country": "South Korea",
		"currency": "$4,088.73"
	},
	{
		"address": "671-9789 At St.",
		"region": "Friesland",
		"postalZip": "13941",
		"country": "Spain",
		"currency": "$1,403.95"
	},
	{
		"address": "Ap #544-2943 Donec Ave",
		"region": "An Giang",
		"postalZip": "5410",
		"country": "Chile",
		"currency": "$6,290.38"
	},
	{
		"address": "Ap #786-9744 Leo. Rd.",
		"region": "Gorontalo",
		"postalZip": "8422",
		"country": "Pakistan",
		"currency": "$4,941.10"
	},
	{
		"address": "2673 Ut Avenue",
		"region": "Western Australia",
		"postalZip": "852143",
		"country": "France",
		"currency": "$6,209.87"
	},
	{
		"address": "4244 Vitae, St.",
		"region": "Wielkopolskie",
		"postalZip": "7668",
		"country": "United States",
		"currency": "$9,673.43"
	},
	{
		"address": "7883 A Av.",
		"region": "Troms og Finnmark",
		"postalZip": "11511",
		"country": "United States",
		"currency": "$3,185.44"
	},
	{
		"address": "P.O. Box 612, 4181 Nonummy Street",
		"region": "Styria",
		"postalZip": "795427",
		"country": "South Korea",
		"currency": "$8,592.78"
	},
	{
		"address": "Ap #922-6619 Phasellus Ave",
		"region": "Puntarenas",
		"postalZip": "6447",
		"country": "Norway",
		"currency": "$5,826.71"
	},
	{
		"address": "590-7939 Vel St.",
		"region": "Puebla",
		"postalZip": "14066",
		"country": "South Africa",
		"currency": "$4,864.90"
	},
	{
		"address": "379-5204 Lobortis St.",
		"region": "Gangwon",
		"postalZip": "12788",
		"country": "Brazil",
		"currency": "$7,405.73"
	},
	{
		"address": "1378 Curabitur Av.",
		"region": "Los Lagos",
		"postalZip": "31869",
		"country": "Norway",
		"currency": "$7,616.08"
	},
	{
		"address": "413-2142 Mollis. Ave",
		"region": "Australian Capital Territory",
		"postalZip": "742861",
		"country": "South Africa",
		"currency": "$4,834.52"
	},
	{
		"address": "Ap #424-9467 Lobortis Street",
		"region": "Limburg",
		"postalZip": "775573",
		"country": "Italy",
		"currency": "$5,274.69"
	},
	{
		"address": "1363 Aliquam, Ave",
		"region": "Magallanes y Antártica Chilena",
		"postalZip": "4297",
		"country": "Costa Rica",
		"currency": "$4,033.45"
	},
	{
		"address": "Ap #127-4581 Non, Ave",
		"region": "Baja California",
		"postalZip": "93192",
		"country": "Vietnam",
		"currency": "$1,917.80"
	},
	{
		"address": "517-1614 Aliquet. Av.",
		"region": "Berkshire",
		"postalZip": "11-38",
		"country": "France",
		"currency": "$5,394.37"
	},
	{
		"address": "Ap #704-6964 Duis St.",
		"region": "Kurgan Oblast",
		"postalZip": "13-641",
		"country": "Vietnam",
		"currency": "$6,149.42"
	},
	{
		"address": "Ap #762-3778 Laoreet Ave",
		"region": "Dōngběi",
		"postalZip": "25881",
		"country": "Singapore",
		"currency": "$4,008.77"
	},
	{
		"address": "481-5971 Massa Ave",
		"region": "Styria",
		"postalZip": "3566",
		"country": "Turkey",
		"currency": "$6,988.74"
	},
	{
		"address": "878-8648 Egestas. St.",
		"region": "Calabarzon",
		"postalZip": "56776",
		"country": "Pakistan",
		"currency": "$7,640.54"
	},
	{
		"address": "682-8264 Eget Street",
		"region": "Sachsen-Anhalt",
		"postalZip": "93-48",
		"country": "Russian Federation",
		"currency": "$8,899.51"
	},
	{
		"address": "715-7544 Ac Av.",
		"region": "Tyumen Oblast",
		"postalZip": "48961",
		"country": "United Kingdom",
		"currency": "$2,471.14"
	}
]